anumoy_verma/__init__.py
anumoy_verma/utils.py
anumoy_verma-0.1.0.dist-info/licenses/LICENSE
anumoy_verma-0.1.0.dist-info/METADATA
anumoy_verma-0.1.0.dist-info/WHEEL
anumoy_verma-0.1.0.dist-info/top_level.txt
anumoy_verma-0.1.0.dist-info/RECORD
