Metadata-Version: 2.4
Name: anumoy_verma
Version: 0.1.0
Summary: My first Python package
Author-email: Anumoy Verma <your-email@example.com>
License: MIT
Requires-Python: >=3.8
License-File: LICENSE
Dynamic: license-file
